MANIFEST.in
README.md
setup.py
humilis_redshift/__init__.py
humilis_redshift/meta.yaml.j2
humilis_redshift/outputs.yaml.j2
humilis_redshift/plugin.py
humilis_redshift/resources.yaml.j2
humilis_redshift.egg-info/PKG-INFO
humilis_redshift.egg-info/SOURCES.txt
humilis_redshift.egg-info/dependency_links.txt
humilis_redshift.egg-info/entry_points.txt
humilis_redshift.egg-info/not-zip-safe
humilis_redshift.egg-info/requires.txt
humilis_redshift.egg-info/top_level.txt