Metadata-Version: 1.1
Name: humilis-redshift
Version: 0.0.8
Summary: Humilis plug-in to deploy a Lambda redshift
Home-page: https://github.com/humilis/humilis-redshift
Author: German Gomez-Herrero, FindHotel BV
Author-email: german@findhotel.net
License: MIT
Platform: UNKNOWN
Classifier: Programming Language :: Python :: 3
